README.md
setup.cfg
setup.py
noterr/__init__.py
noterr/__main__.py
noterr.egg-info/PKG-INFO
noterr.egg-info/SOURCES.txt
noterr.egg-info/dependency_links.txt
noterr.egg-info/entry_points.txt
noterr.egg-info/requires.txt
noterr.egg-info/top_level.txt