Metadata-Version: 2.1
Name: noterr
Version: 1.2.1
Summary: A package to keep track of your note inside the terminal
Home-page: https://github.com/Japroz-Saini/
Author: Japroz Singh Saini
Author-email: sainijaproz@gmail.com
License: MIT
Download-URL: https://github.com/Japroz-Saini/noterr/archive/v1.1.0.tar.gz
Keywords: noterr,japroz singh saini,python,pip
Platform: UNKNOWN
